{
  "number": 3,
  "title_en": "On the Two Hands of Allah",
  "title_ar": "في يدَي الله",
  "title_id": "Tentang Dua Tangan Allah",
  "content_en": "<p>Ibn Khuzaymah dedicates a substantial chapter to the attribute of the Hands of Allah (yadaan), collecting the Quranic verses and prophetic hadiths that establish this attribute and affirming it in accordance with the way of the Salaf: confirmation of the text, denial of resemblance, and silence on the modality.</p>\n<p>The Quranic evidence is abundant. Allah says: 'The Jews said: The Hand of Allah is chained. Their hands are chained and they are cursed for what they said. Rather, His two Hands are extended — He spends however He wills.' (Al-Ma'idah: 64). This verse explicitly affirms two Hands using the dual form in Arabic (yadaani), in a context of refuting the false claim that Allah is miserly or restricted. Allah says: 'O Iblis, what prevented you from prostrating to what I created with My two Hands?' (Sad: 75). This verse specifies that Adam was created by Allah directly with His two Hands — a distinction granting Adam a dignity not shared by any other creature, who was called into existence through the command 'Be.'</p>\n<p>The hadith evidence is likewise extensive. The Prophet, peace be upon him, said: 'Allah will fold up the heavens on the Day of Resurrection, then He will take them in His right Hand, then He will say: I am the King — where are the tyrants? Where are the arrogant?' (Bukhari and Muslim). In another narration: 'Both of His Hands are right Hands.' (Muslim). The Prophet also said: 'Allah created Adam with His Hand, then breathed into him of His spirit, then commanded the angels to prostrate to him.' (Numerous transmissions).</p>\n<p>The critics of attribute affirmation raised the objection that affirming Hands for Allah implies anthropomorphism — making Him resemble His creation. Ibn Khuzaymah and the Athari scholars answered this objection directly: the error lies in the premise. The verse 'There is nothing like unto Him' (Al-Shura: 11) was revealed precisely to prevent any such likening. When we affirm that Allah has two Hands, we do not imagine them as resembling human hands or the hands of any creature. Allah's Hands are an attribute befitting His perfection, majesty, and absolute distinction from creation.</p>\n<p>The distinction the scholars draw is precise: affirming the name or the attribute (ithbat al-wasf) is not the same as affirming resemblance (tashbih). A person can say 'Allah has knowledge' and 'human beings have knowledge' without meaning that the two knowledges are alike in any way. Similarly, affirming that Allah has Hands and that human beings have hands does not imply any similarity. The word may be shared; the reality is utterly different.</p>\n<p>The phrase 'with My two Hands' in Surah Sad is particularly significant to Ibn Khuzaymah's argument. The Mu'tazilah and others sometimes interpreted 'Hand' as meaning 'power' or 'grace.' But if Hand meant merely 'power,' the specification 'with My two Hands' would be redundant — everything Allah creates is by His power. The specification indicates something additional and particular about the creation of Adam, which the Salaf understood as referring to a real attribute.</p>\n<p>Ibn Khuzaymah's approach throughout is that of a hadith scholar: gather the authentic reports, affirm their apparent meaning, apply the theological principle of bila kayf (without asking how), and refuse both the extreme of anthropomorphism and the opposite extreme of negation.</p>",
  "content_id": "<p>Ibn Khuzaymah mendedikasikan satu bab yang substansial untuk sifat Tangan Allah (yadaan), mengumpulkan ayat-ayat Al-Quran dan hadis-hadis nabawi yang menetapkan sifat ini dan menegaskannya sesuai dengan cara para salaf: konfirmasi teks, penolakan penyerupaan, dan diam tentang modalitas.</p><p>Bukti Al-Quran sangat banyak. Allah berfirman: 'Orang-orang Yahudi berkata: Tangan Allah terbelenggu. Tangan merekalah yang terbelenggu dan merekalah yang dilaknat karena apa yang mereka katakan. Bahkan, kedua Tangan-Nya terbuka lebar — Dia menafkahkan sebagaimana Dia kehendaki.' (Al-Ma'idah: 64). Ayat ini secara eksplisit menegaskan dua Tangan menggunakan bentuk dual dalam bahasa Arab (yadaani), dalam konteks membantah klaim palsu bahwa Allah kikir atau terbatas. Allah berfirman: 'Wahai Iblis, apa yang menghalangimu untuk bersujud kepada apa yang Aku ciptakan dengan kedua Tangan-Ku?' (Sad: 75). Ayat ini menentukan bahwa Adam diciptakan oleh Allah secara langsung dengan kedua Tangan-Nya — sebuah keistimewaan yang memberikan Adam martabat yang tidak dimiliki makhluk lain, yang dipanggil ke dalam keberadaan melalui perintah 'Jadilah.'</p><p>Bukti hadis juga sama luasnya. Nabi ﷺ bersabda: 'Allah akan melipat langit pada Hari Kiamat, kemudian Dia akan mengambilnya dengan Tangan kanan-Nya, kemudian Dia berfirman: Akulah Sang Raja — di manakah para penguasa zalim? Di manakah orang-orang sombong?' (Imam Al-Bukhari dan Muslim). Dalam riwayat lain: 'Kedua Tangan-Nya adalah Tangan kanan.' (Muslim). Nabi ﷺ juga bersabda: 'Allah menciptakan Adam dengan Tangan-Nya, kemudian meniupkan ke dalamnya sebagian dari ruh-Nya, kemudian memerintahkan para malaikat untuk bersujud kepadanya.' (Banyak jalur periwayatan).</p><p>Para pengkritik penegasan sifat mengajukan keberatan bahwa menegaskan Tangan bagi Allah mengimplikasikan antropomorfisme — menjadikan-Nya menyerupai ciptaan-Nya. Ibn Khuzaymah dan para ulama Athari menjawab keberatan ini secara langsung: kesalahan terletak pada premisnya. Ayat 'Tidak ada sesuatupun yang serupa dengan-Nya' (Al-Syura: 11) diturunkan justru untuk mencegah penyerupaan semacam itu. Ketika kita menegaskan bahwa Allah memiliki dua Tangan, kita tidak membayangkannya menyerupai tangan manusia atau tangan makhluk apapun. Tangan Allah adalah sifat yang sesuai dengan kesempurnaan, keagungan, dan keunikan-Nya yang mutlak dari ciptaan.</p><p>Perbedaan yang ditarik para ulama sangat tepat: menegaskan nama atau sifat (ithbat al-wasf) tidak sama dengan menegaskan penyerupaan (tasyabuh). Seseorang dapat mengatakan 'Allah memiliki ilmu' dan 'manusia memiliki ilmu' tanpa bermaksud bahwa kedua ilmu itu serupa dalam hal apapun. Demikian pula, menegaskan bahwa Allah memiliki Tangan dan bahwa manusia memiliki tangan tidak mengimplikasikan kesamaan apapun. Katanya mungkin sama; realitasnya sangat berbeda.</p><p>Frasa 'dengan kedua Tangan-Ku' dalam Surah Sad sangat signifikan bagi argumen Ibn Khuzaymah. Kaum Mu'tazilah dan lainnya kadang-kadang menafsirkan 'Tangan' sebagai 'kekuasaan' atau 'karunia.' Namun jika Tangan hanya berarti 'kekuasaan,' maka spesifikasi 'dengan kedua Tangan-Ku' akan menjadi berlebihan — segala sesuatu yang Allah ciptakan adalah dengan kekuasaan-Nya. Spesifikasi ini menunjukkan sesuatu yang tambahan dan khusus tentang penciptaan Adam, yang para salaf pahami sebagai merujuk kepada sifat yang nyata.</p><p>Pendekatan Ibn Khuzaymah secara keseluruhan adalah pendekatan seorang ulama hadis: kumpulkan riwayat-riwayat yang sahih, tegaskan makna zahirnya, terapkan prinsip teologis bila kayf (tanpa bertanya bagaimana), dan tolak baik ekstrem antropomorfisme maupun ekstrem penafian yang berlawanan.</p>",
  "subject_tags": [
    "aqeedah",
    "hadith"
  ],
  "topic_tags": [
    "tawhid",
    "names-and-attributes"
  ],
  "era_tags": [
    "fourth-century-ah"
  ],
  "madhab_tags": [],
  "content_type_tags": [
    "narration",
    "explanation"
  ],
  "keywords": [
    "kitab al-tawhid",
    "ibn khuzaymah",
    "divine attributes",
    "hadith aqeedah",
    "names and attributes",
    "tawhid"
  ],
  "qa_passed": true,
  "qa_errors": [],
  "content_ar": "<p>يُعالج هذا الفصل إثبات صفة اليدين لله تعالى كما وردت في الآيات القرآنية الكريمة كقوله تعالى: «لِمَا خَلَقْتُ بِيَدَيَّ» وقوله: «بَلْ يَدَاهُ مَبْسُوطَتَانِ». ويُثبت ابن خزيمة هذه الصفة على الوجه الذي يليق بالله دون تشبيه.</p>\n<p>ويستعرض ما ورد في القرآن والسنة من ذكر يدَي الله، ويرد على من أوّل هذه النصوص بالقدرة أو النعمة، موضحاً أن التأويل في هذا المقام يُفضي إلى تعطيل الصفات الثابتة بالنص.</p>\n<p>ويُبيّن أن مذهب السلف الصالح في مثل هذه الصفات هو الإثبات مع نفي المماثلة والكيفية، استناداً إلى قوله تعالى: «لَيْسَ كَمِثْلِهِ شَيْءٌ وَهُوَ السَّمِيعُ الْبَصِيرُ».</p><p>وكتاب التوحيد للإمام ابن خزيمة من أمهات كتب العقيدة السلفية التي أثبتت صفات الله تعالى الواردة في الكتاب والسنة إثباتاً صريحاً بلا تأويل ولا تعطيل. وقد جمع فيه صاحبه الأحاديث الدالة على ذلك ودافع عنها بالحجة والبرهان، مما جعله مرجعاً لا غنى عنه في علم التوحيد والصفات عند أهل السنة والجماعة.</p>",
  "content_ar_source": "lp-c3-msa"
}