{
  "number": 4,
  "title_en": "The Caliphate of Umar: Governance and Expansion",
  "title_id": "Kekhalifahan Umar: Pemerintahan dan Perluasan",
  "content_en": "<p>Umar ibn al-Khattab's ten-year caliphate (13-23 AH / 634-644 CE) represents one of the most consequential decades in Islamic history and arguably in world history. The Islamic state expanded from the Arabian Peninsula to encompass the entire Fertile Crescent, Egypt, Persia, and parts of Central Asia — an expansion achieved with extraordinary speed but also with a quality of just governance that its new subjects often found superior to what they had known under the Byzantine and Sassanid empires.</p>\n<p>The administrative genius that Umar brought to the caliphate was without precedent in the Muslim community. He created the diwan — a systematic register for distributing state revenues to eligible recipients — establishing the first Islamic welfare state. He appointed governors with clear lines of accountability, conducted regular inspections of provincial administration, and maintained an open-door policy through which any subject could bring a grievance against any official, including Umar himself. His famous walks through the streets of Madinah at night, checking on the welfare of his subjects, established a model of personal governance that subsequent Islamic rulers aspired to emulate.</p>\n<p>The military expansion under Umar was organized with a strategic sophistication that leveraged the qualities of the Muslim fighters while minimizing unnecessary civilian harm. The decisive battles of al-Qadisiyyah (636 CE), which broke Sassanid power in Iraq, and the Yarmouk (636 CE), which shattered Byzantine control of Syria and Palestine, were won not merely through military superiority but through the extraordinary morale of an army that believed itself engaged in a divinely directed enterprise. Umar himself did not command these campaigns directly but chose generals with proven ability and maintained strategic oversight from Madinah.</p>\n<p>Perhaps the most telling episode of Umar's caliphate is the surrender of Jerusalem in 638 CE. When the city agreed to surrender only to the caliph personally, Umar made the long journey from Madinah — accompanied by a single servant and a single camel, taking turns riding as a demonstration of the equality that Islam proclaimed. He arrived in worn clothing that impressed and surprised the Byzantine dignitaries who received him. His insistence on entering the city in this manner, and his assurance of safety to the city's Christian and Jewish inhabitants, established a model of religious tolerance in governance that subsequent Islamic rulers of Jerusalem largely maintained.</p>\n<p>Umar's fiscal policies were groundbreaking. He refused to redistribute conquered agricultural lands to the conquering armies (a common practice in ancient warfare), instead retaining them as productive assets for the entire community and taxing them to fund the state. This decision, controversial at the time, prevented the concentration of land wealth in the hands of the military elite and maintained the productivity of agricultural regions that might otherwise have been disrupted. It demonstrated a long-term economic thinking that complemented his immediate military and political successes.</p>",
  "content_id": "<p>Kekhalifahan Umar bin Al-Khaththab selama sepuluh tahun (13-23 H / 634-644 M) mewakili salah satu dekade yang paling berpengaruh dalam sejarah Islam dan boleh dibilang dalam sejarah dunia. Negara Islam berkembang dari Semenanjung Arabia untuk mencakup seluruh Bulan Sabit Subur, Mesir, Persia, dan sebagian Asia Tengah — perluasan yang dicapai dengan kecepatan luar biasa tetapi juga dengan kualitas pemerintahan yang adil yang sering kali ditemukan lebih baik oleh rakyat baru dibandingkan apa yang mereka ketahui di bawah kekaisaran Byzantium dan Sassaniyah.</p>\n<p>Jenius administratif yang dibawa Umar ke kekhalifahan tidak ada presedennya dalam komunitas Muslim. Ia menciptakan diwan — daftar sistematis untuk mendistribusikan pendapatan negara kepada penerima yang berhak — meletakkan dasar negara kesejahteraan Islam pertama. Ia mengangkat para gubernur dengan garis akuntabilitas yang jelas, melakukan inspeksi rutin terhadap administrasi provinsi, dan mempertahankan kebijakan pintu terbuka di mana rakyat mana pun dapat membawa keluhan terhadap pejabat mana pun, termasuk Umar sendiri. Perjalanannya yang terkenal menyusuri jalanan Madinah di malam hari, memeriksa kesejahteraan rakyatnya, menetapkan model pemerintahan personal yang dicita-citakan oleh penguasa-penguasa Islam berikutnya.</p>\n<p>Perluasan militer di bawah Umar diorganisasikan dengan kecanggihan strategis yang memanfaatkan kualitas-kualitas para pejuang Muslim sekaligus meminimalkan kerugian sipil yang tidak perlu. Pertempuran-pertempuran penentu Al-Qadisiyyah (636 M), yang menghancurkan kekuatan Sassaniyah di Irak, dan Yarmuk (636 M), yang menghancurkan kontrol Byzantium atas Syam dan Palestina, dimenangkan bukan semata-mata melalui keunggulan militer tetapi melalui moral luar biasa sebuah pasukan yang meyakini dirinya terlibat dalam suatu perusahaan yang dikendalikan secara ilahi. Umar sendiri tidak memimpin kampanye-kampanye ini secara langsung tetapi memilih para jenderal dengan kemampuan yang terbukti dan mempertahankan pengawasan strategis dari Madinah.</p>\n<p>Mungkin episode yang paling berkesan dari kekhalifahan Umar adalah penyerahan Yerusalem pada tahun 638 M. Ketika kota itu setuju untuk menyerah hanya kepada khalifah secara pribadi, Umar melakukan perjalanan panjang dari Madinah — ditemani oleh seorang pelayan dan seekor unta, bergantian menunggang sebagai demonstrasi kesetaraan yang diproklamirkan Islam. Ia tiba dengan pakaian lusuh yang mengesankan dan mengejutkan para tokoh Byzantium yang menerimanya. Sikerasannya memasuki kota dengan cara ini, dan jaminan keamanannya kepada penduduk Kristen dan Yahudi kota itu, menetapkan model toleransi beragama dalam pemerintahan yang sebagian besar dipertahankan oleh penguasa-penguasa Islam Yerusalem berikutnya.</p>\n<p>Kebijakan-kebijakan fiskal Umar bersifat revolusioner. Ia menolak mendistribusikan kembali tanah-tanah pertanian yang ditaklukkan kepada tentara-tentara penakluk — praktik umum dalam peperangan kuno — dan malahan mempertahankannya sebagai aset produktif bagi seluruh komunitas dan mengenakan pajak atasnya untuk mendanai negara. Keputusan ini, yang kontroversial pada masanya, mencegah konsentrasi kekayaan tanah di tangan elit militer dan mempertahankan produktivitas wilayah-wilayah pertanian yang mungkin sebaliknya terganggu. Ini menunjukkan pemikiran ekonomi jangka panjang yang melengkapi keberhasilan-keberhasilan militer dan politiknya yang segera.</p>",
  "subject_tags": [
    "biography",
    "history"
  ],
  "topic_tags": [
    "companions",
    "sahabah",
    "caliphate-history"
  ],
  "era_tags": [
    "modern"
  ],
  "madhab_tags": [
    "no-madhab"
  ],
  "content_type_tags": [
    "biography-content",
    "historical-account"
  ],
  "keywords": [
    "umar ibn al-khattab",
    "biography",
    "second caliph",
    "companion biography"
  ],
  "qa_passed": true,
  "qa_errors": [],
  "title_ar": "خلافة عمر: الحوكمة والفتوحات",
  "content_ar": "<p>تمثّل خلافة عمر بن الخطاب العشرية (13-23هـ / 634-644م) من أكثر العقود أثرًا في التاريخ الإسلامي، بل ربما في تاريخ العالم كله. فقد امتدت الدولة الإسلامية من جزيرة العرب لتشمل بلاد الرافدين كلها ومصر وفارس وأجزاءً من آسيا الوسطى — فتحٌ أُنجز بسرعة مذهلة، مع جودة حوكمة وجد فيها أهل البلاد المفتوحة كثيرًا مما افتقروا إليه في ظل الإمبراطوريتين البيزنطية والساسانية.</p>\n<p>وتُولي ترجمة الصلابي لخلافة عمر عنايةً فائقة للبنية الإدارية التي أسسها؛ فقد ابتكر عمر — أو طوّر ووحّد — كثيرًا من المؤسسات التي ستشكّل العمود الفقري للحضارة الإسلامية: الديوان لتسجيل المقاتلين وصرف مخصصاتهم، والتقويم الهجري القائم على سنة الهجرة، وتعيين القضاة وإحكام استقلاليتهم، واستحداث شبكة من المحافظات يحكمها ولاة خاضعون للمساءلة أمام المركز.</p>\n<p>وتُقدَّم معارك اليرموك (636م) والقادسية (636-637م) فتحًا للشام والعراق كمواجهات عسكرية ذات طابع استراتيجي بالغ. ويصف الصلابي كيف أشرف عمر على هذه الحملات من المدينة المنورة، مُسيِّرًا جيوشه وموزعًا قواته توزيعًا يُجمع فيه بين المبادأة العسكرية الجريئة والتدبير الواقعي المتأني.</p>\n<p>أما الجانب الإداري في حكم عمر فلا يقل أهمية عن الجانب العسكري؛ فقد مضى في معظم عهده على درب الانضباط والتقشف المشددين، يحاسب الولاة محاسبةً صارمة، ويُعزل من تشير إليه أصابع الاتهام بالفساد بصرف النظر عن مكانته. وقد روى بعض المؤرخين أنه أعلن ذات موسم حج: «من كان يعلم علي ظلمًا أو جورًا فليقم فليقله» — ويُقال إن رجلًا عاديًّا قام فاعترضه فلم يزجره.</p>",
  "content_ar_source": "original"
}