{
  "number": 4,
  "title_en": "The Imamate, Political Theology, and Community",
  "title_ar": "الإمامة والفكر السياسي والجماعة",
  "title_id": "Imamah, Teologi Politik, dan Komunitas",
  "content_id": "Al-Iqtisad mencakup bagian substansial tentang Imamah dan teologi politik yang secara historis sangat menarik. Pembahasan al-Ghazali tentang topik ini mencerminkan baik posisi Sunni klasik maupun keadaan politik spesifik zamannya, ketika Kekhalifahan Abbasiyah sebagian besar berada di bawah kendali Sultan Seljuk dan pertanyaan-pertanyaan tentang hubungan antara otoritas keagamaan dan kekuasaan politik mendesak secara praktis.\n\nPosisi al-Ghazali tentang Imamah secara umum dianggap sebagai adaptasi pragmatis teologi politik Sunni sebelumnya terhadap realitas zamannya. Posisi Sunni klasik telah menegaskan bahwa Imam (khalifah) harus memenuhi syarat-syarat tertentu, termasuk keturunan dari Quraysy, kesalehan pribadi, pengetahuan, dan kemampuan praktis untuk memerintah. Di era al-Ghazali, khalifah yang memenuhi semua syarat ini dalam pengertian klasik penuh tidak ada, namun fungsi-fungsi praktis pemerintahan Islam — memelihara ketertiban, melindungi komunitas, mengadministrasikan keadilan — perlu dilaksanakan oleh seseorang.\n\nRespons pragmatis al-Ghazali adalah dengan berpendapat bahwa kondisi-kondisi untuk Imamah harus dipahami dalam terang keadaan aktual: ketika kandidat yang sepenuhnya memenuhi syarat tidak tersedia, lebih baik mengakui sosok yang kurang ideal tetapi dapat memerintah secara nyata daripada bersikeras pada kesempurnaan teoretis sambil membiarkan komunitas tanpa kepemimpinan efektif. Posisi ini telah digambarkan oleh para sarjana sebagai semacam realisme yuridis yang mempertahankan prinsip-prinsip teologis formal sambil mengakomodasi realitas politik.\n\nBagian ini juga membahas pertanyaan tentang kewajiban-kewajiban Muslim biasa berkenaan dengan tatanan politik. Orientasi umum al-Ghazali — konsisten dengan mayoritas tradisi Sunni — adalah menuju stabilitas dan penghindaran fitnah (perselisihan sipil). Ia sangat prihatin tentang konsekuensi-konsekuensi destruktif dari pergolakan politik bagi komunitas Muslim dan percaya bahwa fungsi-fungsi keilmuan dan keagamaan Islam dapat dipertahankan bahkan di bawah pengaturan-pengaturan politik yang tidak sempurna, selama para ulama mempertahankan otonomi mereka dalam masalah-masalah keagamaan.\n\nPembahasan teologi politik dalam Al-Iqtisad ini mencerminkan pendekatan Asy'ari yang lebih luas tentang hubungan antara teologi dan kehidupan beragama yang praktis. Teologi bukanlah spekulasi abstrak semata tetapi menyediakan landasan rasional bagi seluruh cara hidup Islam, termasuk dimensi-dimensi politiknya dan sosialnya. Moderasi al-Ghazali — iqtisad dari judul itu — meluas dari metode teologis ke pemikiran politik: menghindari baik ekstremisme mereka yang akan menarik semua kerja sama dari pemerintahan yang tidak sempurna maupun kepuasan diri mereka yang akan sepenuhnya meninggalkan fungsi kritis keilmuan keagamaan.",
  "content_en": "<p>Al-Iqtisad includes a substantial section on the Imamate and political theology that is of particular historical interest. Al-Ghazali's treatment of this topic reflects both the classical Sunni position and the specific political circumstances of his time, when the Abbasid caliphate was largely under the control of Seljuk sultans and questions about the relationship between religious authority and political power were practically urgent.</p>\n<p>Al-Ghazali's position on the Imamate is generally considered a pragmatic adaptation of earlier Sunni political theology to the realities of his time. The classical Sunni position had insisted that the Imam (caliph) must meet certain qualifications, including descent from Quraysh, personal piety, knowledge, and the practical capacity to govern. In al-Ghazali's era, caliphs who met all these qualifications in the full classical sense did not exist, yet the practical functions of Islamic governance — maintaining order, protecting the community, administering justice — needed to be exercised by someone.</p>\n<p>Al-Ghazali's pragmatic response was to argue that the conditions for the Imamate should be understood in light of actual circumstances: when a fully qualified candidate is unavailable, it is better to recognize a less-than-ideal figure who can actually govern than to insist on theoretical perfection while leaving the community without effective leadership. This position has been described by scholars as a kind of juristic realism that preserved formal theological principles while accommodating political reality.</p>\n<p>The section also addresses the question of the obligations of ordinary Muslims regarding the political order. Al-Ghazali's general orientation — consistent with the majority Sunni tradition — was toward stability and the avoidance of fitna (civil strife). He was deeply concerned about the destructive consequences of political upheaval for Muslim communities and believed that the scholarly and religious functions of Islam could be maintained even under imperfect political arrangements, as long as scholars retained their autonomy in religious matters.</p>\n<p>This treatment of political theology in Al-Iqtisad reflects the broader Ash'ari approach to the relationship between theology and practical religious life. Theology is not merely abstract speculation but provides the rational grounding for the entire Islamic way of life, including its political and social dimensions. Al-Ghazali's moderation — the iqtisad of the title — extends from theological method into political thought: avoiding both the extremism of those who would withdraw all cooperation from imperfect governance and the complacency of those who would abandon the critical function of religious scholarship entirely.</p>",
  "subject_tags": [
    "aqeedah",
    "philosophy"
  ],
  "topic_tags": [
    "tawhid",
    "names-and-attributes",
    "ahl-us-sunnah"
  ],
  "era_tags": [
    "sixth-century-ah"
  ],
  "madhab_tags": [
    "shafii"
  ],
  "content_type_tags": [
    "explanation"
  ],
  "keywords": [
    "al-iqtisad",
    "al-ghazali",
    "moderation in belief",
    "ashari theology",
    "divine attributes",
    "prophets",
    "eschatology"
  ],
  "qa_passed": true,
  "qa_errors": []
}