{
  "number": 3,
  "title_en": "Key Themes: Ijaz al-Quran, Hermeneutics, and the Quranic Sciences",
  "title_ar": "الموضوعات الكبرى: إعجاز القرآن والتأويل وعلوم القرآن",
  "content_en": "<p>Al-Burhan addresses the full range of Quranic sciences, but several of its sections have attracted particular scholarly attention for their depth and originality.</p>\n<p>The section on ijaz al-Quran — the inimitability or miraculous nature of the Quran — is among the most developed treatments of this topic in the classical tradition. Az-Zarkashi surveys the various theories about what constitutes the Quran's inimitability: its linguistic and rhetorical uniqueness (the dominant theory), its content and knowledge of unseen matters, the incapacity that Allah places on humans to imitate it (sarfa), and its comprehensive spiritual effect on hearers. His analysis of the linguistic and rhetorical dimension is particularly thorough, drawing on the full apparatus of classical Arabic rhetoric to analyze the Quran's stylistic features.</p>\n<p>The sections on Meccan and Medinan surahs — distinguishing the two categories, their characteristics, and the significance of the distinction for interpretation — provide one of the most systematic treatments of this foundational topic. Az-Zarkashi surveys the classical criteria for Meccan and Medinan classification, notes cases where different scholars have disagreed, and draws out the interpretive implications of the distinction for understanding specific surahs and verses.</p>\n<p>The hermeneutical sections are particularly valuable for students of tafsir methodology. Az-Zarkashi discusses: what qualifies as a valid interpretation of the Quran (tafsir) as opposed to personal opinion (ra'y mazmum); the rules for interpreting figurative and allegorical language; the conditions under which the hadith tradition is authoritative for Quranic interpretation; and the principles of reconciling apparently contradictory Quranic passages. These discussions are conducted with the legal theorist's precision and provide a methodological foundation for Quranic interpretation.</p>\n<p>The sections on abrogation (naskh) provide a comprehensive survey of the classical theory: the different types of abrogation (of recitation, of ruling, of both), the criteria for determining that abrogation has occurred, and specific examples. This is a topic on which classical scholars disagreed substantially, and az-Zarkashi's survey of the disagreements is particularly thorough.</p>\n<p>The linguistic sections — covering Arabisms and non-Arabic words in the Quran, the dialects present in Quranic language, and the vocabulary of divine address — reflect az-Zarkashi's thorough grounding in Arabic grammar and linguistics applied to the unique case of Quranic language.</p>",
  "qa_passed": true,
  "content_id": "<p>Al-Burhan membahas keseluruhan cabang ilmu-ilmu Al-Qur'an, namun beberapa bagiannya telah menarik perhatian khusus para ulama karena kedalaman dan orisinalitasnya.</p>\n<p>Bagian tentang i'jaz al-Qur'an — kemukjizatan atau sifat tidak tertandingi dari Al-Qur'an — termasuk di antara pembahasan paling mendalam mengenai topik ini dalam tradisi klasik. Az-Zarkashi mengulas berbagai teori tentang apa yang membentuk kemukjizatan Al-Qur'an: keunikan bahasa dan retorikanya (teori yang paling dominan), kandungan dan pengetahuannya tentang hal-hal gaib, ketidakmampuan yang Allah timpakan kepada manusia untuk menirunya (sarfah), serta pengaruh spiritual menyeluruhnya terhadap para pendengar. Analisisnya terhadap dimensi kebahasaan dan retorika sangat mendalam, dengan memanfaatkan seluruh perangkat retorika Arab klasik untuk menganalisis ciri-ciri stilistika Al-Qur'an.</p>\n<p>Bagian-bagian tentang surah Makkiyyah dan Madaniyyah — yang membedakan kedua kategori tersebut, karakteristik masing-masing, serta signifikansi perbedaan itu bagi penafsiran — menyajikan salah satu pembahasan paling sistematis mengenai topik fundamental ini. Az-Zarkashi mengulas kriteria klasik dalam pengklasifikasian Makkiyyah dan Madaniyyah, mencatat kasus-kasus di mana para ulama berbeda pendapat, serta menguraikan implikasi penafsiran dari perbedaan tersebut dalam memahami surah dan ayat tertentu.</p>\n<p>Bagian-bagian hermeneutika sangat berharga bagi para penuntut ilmu metodologi tafsir. Az-Zarkashi membahas: apa yang memenuhi syarat sebagai penafsiran Al-Qur'an yang sahih (tafsir) sebagai lawan dari pendapat pribadi (ra'y mazmum); kaidah-kaidah dalam menafsirkan bahasa kiasan dan alegoris; syarat-syarat yang menjadikan tradisi hadits bersifat otoritatif bagi penafsiran Al-Qur'an; serta prinsip-prinsip dalam menyelaraskan ayat-ayat Al-Qur'an yang tampak saling bertentangan. Pembahasan-pembahasan ini disampaikan dengan presisi seorang ahli ushul fiqh dan memberikan landasan metodologis bagi penafsiran Al-Qur'an.</p>\n<p>Bagian-bagian tentang nasakh menyajikan tinjauan menyeluruh terhadap teori klasik: berbagai jenis nasakh (nasakh tilawah, nasakh hukum, nasakh keduanya), kriteria untuk menentukan telah terjadinya nasakh, serta contoh-contoh spesifiknya. Ini merupakan topik yang menjadi perdebatan signifikan di kalangan ulama klasik, dan tinjauan az-Zarkashi terhadap perbedaan-perbedaan pendapat tersebut sangat komprehensif.</p>\n<p>Bagian-bagian kebahasaan — yang mencakup kata-kata Arab dan kata serapan non-Arab dalam Al-Qur'an, dialek-dialek yang terdapat dalam bahasa Al-Qur'an, serta kosakata khitab ilahi — mencerminkan landasan az-Zarkashi yang kokoh dalam tata bahasa dan linguistik Arab yang diterapkan pada keistimewaan bahasa Al-Qur'an.</p>",
  "title_id": "Tema-tema Utama: Ijaz al-Quran, Hermeneutika, dan Ilmu-ilmu Al-Quran",
  "content_ar": "<p>يُولي الزركشي في البرهان اهتماماً بالغاً لمسألة إعجاز القرآن الكريم وأوجهه المتعددة. ويرى أن الإعجاز لا يقتصر على الجانب اللغوي والبياني بل يتجاوزه إلى الإعجاز العلمي والتشريعي والتاريخي والغيبي. غير أن المحور الذي يُركّز عليه أكثر هو الإعجاز البياني والأسلوبي الذي لمسه العرب الفصحاء ففُتنوا به وعجزوا عن معارضته.</p><p>ومن أبرز ما يطرحه الكتاب في هذا الباب: مسألة أوجه التعبير القرآني وما فيها من دقة البيان وحسن التصوير وجمال التشبيه والاستعارة والكناية. وقد استشهد الزركشي بآيات كثيرة يُحلّل فيها الأسلوب البياني تحليلاً نقدياً دقيقاً يُظهر مدى تفوق القرآن على أفصح كلام العرب.</p><p>وتُعالج فصول مستقلة في البرهان موضوع التأويل والتفسير وما يجوز منه وما لا يجوز، وهي فصول ذات أهمية منهجية بالغة للمفسرين. ويُبيّن الزركشي أن التفسير بالرأي المجرد دون اتكاء على الرواية والسنة وأقوال الصحابة والتابعين محفوف بمخاطر جسيمة قد تُفضي إلى الانحراف عن المقصود الإلهي.",
  "content_ar_source": "lp-b-msa"
}