{
  "number": 4,
  "title_en": "Scholarly Reception and Lasting Influence",
  "title_ar": "التلقي العلمي والأثر المستمر",
  "title_id": "Penerimaan Ilmiah dan Pengaruh yang Berkelanjutan",
  "content_en": "<p>Tadhkirat al-Huffaz has been recognized as an essential reference in hadith sciences and Islamic intellectual history from the time of its composition. Later scholars of hadith who needed biographical information about major transmitters regularly consulted adh-Dhahabi's work. Ibn Hajar al-Asqalani, who was adh-Dhahabi's most important intellectual successor, drew on Tadhkirat al-Huffaz extensively, incorporating its biographies and assessments into his own more comprehensive biographical works.</p>\n<p>The work's influence on the history of Islamic scholarship is difficult to overstate. It provided later generations with a framework for understanding the development of hadith scholarship: who the major figures were, when they lived, what they contributed, how they evaluated one another. This framework has shaped how the tradition has understood itself, and it continues to shape how students and scholars of hadith understand the history of their discipline.</p>\n<p>In the modern academic study of hadith, Tadhkirat al-Huffaz is a primary source for intellectual biography and for the history of the sciences. Scholars studying the development of the major hadith collections, the formation of the canonical status of specific books, or the intellectual relationships between major scholars of the classical period all engage with it as foundational evidence. The fact that adh-Dhahabi was himself a major figure in the tradition he was documenting gives his evaluations particular authority but also requires some critical awareness of his perspective.</p>\n<p>The work has been used as a basis for broader studies of Islamic scholarship in different periods and regions. Its generation-by-generation organization provides a convenient framework for periodization, and its geographic spread — it includes scholars from Iraq, Persia, the Levant, Egypt, the Hijaz, and North Africa — makes it useful for studies of the spread of hadith scholarship across the Islamic world. As the definitive reference for the biographies of the major hadith scholars, Tadhkirat al-Huffaz also serves an important function in the authentication process itself: when scholars want to understand who a major hadith critic was, when he lived, with whom he studied, and how his judgments were received, they turn first to this work and to Siyar Alam an-Nubala for the fullest available documentation.</p>",
  "content_id": "Tadzkirat al-Huffaz telah diakui sebagai referensi yang sangat penting dalam ilmu-ilmu hadis dan sejarah intelektual Islam sejak waktu penulisannya. Ulama-ulama hadis berikutnya yang memerlukan informasi biografis tentang perawi-perawi utama secara rutin mengonsultasikan karya al-Dzahabi. Ibn Hajar al-Asqalani, yang merupakan penerus intelektual terpenting al-Dzahabi, menggali Tadzkirat al-Huffaz secara ekstensif, memasukkan biografi-biografi dan penilaian-penilaiannya ke dalam karya-karya biografi yang lebih komprehensif miliknya sendiri.\n\nPengaruh karya ini pada sejarah ilmu Islam sulit untuk dilebih-lebihkan. Karya ini menyediakan generasi-generasi berikutnya dengan kerangka untuk memahami perkembangan ilmu hadis: siapa tokoh-tokoh utamanya, kapan mereka hidup, apa yang mereka kontribusikan, bagaimana mereka mengevaluasi satu sama lain. Kerangka ini telah membentuk bagaimana tradisi memahami dirinya sendiri, dan terus membentuk bagaimana para pelajar dan ulama hadis memahami sejarah disiplin mereka.\n\nDalam studi akademik modern tentang hadis, Tadzkirat al-Huffaz adalah sumber primer untuk biografi intelektual dan untuk sejarah ilmu-ilmu. Para ulama yang mempelajari perkembangan koleksi-koleksi hadis utama, pembentukan status kanonik kitab-kitab spesifik, atau hubungan-hubungan intelektual antara ulama-ulama utama dari periode klasik semuanya terlibat dengannya sebagai bukti fundamental. Fakta bahwa al-Dzahabi sendiri adalah tokoh utama dalam tradisi yang sedang beliau dokumentasikan memberikan evaluasi-evaluasinya otoritas khusus tetapi juga memerlukan kesadaran kritis terhadap perspektifnya.\n\nKarya ini telah digunakan sebagai dasar untuk studi-studi yang lebih luas tentang ilmu Islam di berbagai periode dan wilayah. Organisasinya berdasarkan generasi-demi-generasi menyediakan kerangka yang nyaman untuk periodisasi, dan persebaran geografisnya — mencakup ulama-ulama dari Irak, Persia, Levant, Mesir, Hijaz, dan Afrika Utara — menjadikannya berguna untuk studi-studi tentang penyebaran ilmu hadis di seluruh dunia Islam. Sebagai referensi definitif untuk biografi-biografi ulama-ulama hadis utama, Tadzkirat al-Huffaz juga melayani fungsi penting dalam proses autentifikasi itu sendiri: ketika ulama-ulama ingin memahami siapa seorang kritikus hadis utama, kapan beliau hidup, dengan siapa beliau belajar, dan bagaimana penilaian-penilaiannya diterima, mereka terlebih dahulu berpaling kepada karya ini dan kepada Siyar A'lam al-Nubala' untuk dokumentasi paling lengkap yang tersedia.",
  "subject_tags": [
    "hadith-sciences",
    "biography"
  ],
  "topic_tags": [
    "narrator-biography",
    "rijal",
    "scholar-biography"
  ],
  "era_tags": [
    "eighth-century-ah"
  ],
  "madhab_tags": [
    "no-madhab"
  ],
  "content_type_tags": [
    "biography-content"
  ],
  "keywords": [
    "tadhkirat al-huffaz",
    "dhahabi",
    "hadith masters",
    "huffaz biographies"
  ],
  "qa_passed": true,
  "qa_errors": []
}