{
  "number": 3,
  "title_en": "Key Content and Legal Themes",
  "title_ar": "المحتوى الرئيسي والموضوعات الفقهية",
  "title_id": "Konten Utama dan Tema-Tema Hukum",
  "content_id": "Rawdat at-Talibin dihargai terutama karena kejelasan dan keandalan keputusan-keputusan hukumnya. Di seluruh bab-babnya, karya ini mencerminkan komitmen an-Nawawi untuk mengidentifikasi pendapat-pendapat yang paling berdasar teks dan paling dapat dipertahankan secara intelektual dalam tradisi Syafi'i. Dalam hukum ritual, bab-bab tentang salat sangat dikenal karena penanganan cermatnya atas unsur-unsur wajib salat versus unsur-unsur sunnah, serta penanganan sistematis kasus-kasus di mana ibadah dilakukan dalam keadaan terpaksa atau tidak mampu.\n\nBab-bab tentang muamalah mencerminkan lingkungan komersial yang canggih di Suriah dan Mesir abad pertengahan. An-Nawawi membahas jual beli beserta syarat-syarat dan cacat-cacatnya, aturan khiyar (hak pilih), akad salam (jual beli di muka), musyarakah (kemitraan), dan wakaf. Pembahasan riba sangat hati-hati, menelaah berbagai kategori bunga dan kondisi-kondisi di mana masing-masing berlaku. Bab-bab tentang sewa menyewa membahas pengaturan kerja, mengangkat pertanyaan yang relevan bagi serikat pengrajin, sewa pertanian, dan layanan profesional.\n\nHukum pernikahan dan keluarga dibahas dengan sangat terperinci. An-Nawawi membahas syarat-syarat akad nikah yang sah, mahar, hak dan kewajiban pasangan, aturan poligini, serta berbagai bentuk cerai — talak, khul', faskh, dan ila'. Bab-bab tentang hak asuh dan nafkah anak mencerminkan kepeduliannya terhadap kesejahteraan pihak yang lebih lemah dalam sengketa hukum. Bab-bab warisan menerapkan aturan-aturan pembagian harta Al-Qur'an pada struktur keluarga yang kompleks dengan berbagai kemungkinan.\n\nFitur khas Rawdat al-Talibin adalah pembahasan prosedur peradilan. An-Nawawi menjelaskan persyaratan tuntutan yang sah, aturan pembuktian, kondisi diterimanya atau ditolaknya kesaksian, dan standar untuk menjatuhkan putusan. Ini mencerminkan audiens karya tersebut: bukan hanya pelajar tetapi juga para qadi yang aktif bertugas yang membutuhkan panduan otoritatif tentang hukum acara. Sepanjang karya, bahasa an-Nawawi terkendali dan tepat, tidak pernah mengorbankan kejelasan demi keringkasan atau keringkasan demi kelengkapan.",
  "content_en": "<p>Rawdat at-Talibin is valued above all for the clarity and reliability of its legal determinations. Across all its chapters, the work exemplifies Al-Nawawi's commitment to identifying the most textually grounded and intellectually defensible positions within the Shafi'i tradition. In ritual law, the chapters on prayer are particularly celebrated for their careful treatment of the prayer's obligatory elements versus its recommended elements, and for the systematic treatment of cases in which acts of worship are performed under duress or incapacity.</p>\n<p>The chapters on transactions reflect the sophisticated commercial environment of medieval Syria and Egypt. Al-Nawawi addresses sales, their conditions and defects, the rules of option (khiyar), the contract of salam (forward sale), musharakah (partnership), and waqf. The treatment of riba is especially careful, examining the various categories of interest and the conditions under which they apply. The chapters on lease and hire discuss labor arrangements, raising questions relevant to craft guilds, agricultural tenancy, and professional services.</p>\n<p>Marriage and family law is treated with great detail. Al-Nawawi addresses the conditions for a valid marriage contract, the mahr (dower), the rights and obligations of spouses, the rules for polygyny, and the various forms of divorce — talaq, khul', faskh, and ila'. The chapters on custody and child support reflect his concern for the welfare of the weaker parties in a legal dispute. The inheritance chapters apply the Quranic rules of succession to complex family structures with numerous contingencies.</p>\n<p>A distinctive feature of the Rawda is its treatment of judicial procedure. Al-Nawawi explains the requirements for a valid claim, the rules of evidence, the conditions under which testimony is accepted or rejected, and the standards for rendering a judgment. This reflects the work's audience: not only students but practicing qadis who needed authoritative guidance on procedural law. Throughout, Al-Nawawi's language is controlled and precise, never sacrificing clarity for brevity or brevity for completeness.</p>",
  "subject_tags": [
    "fiqh"
  ],
  "topic_tags": [
    "tahara",
    "salah",
    "zakah",
    "sawm",
    "hajj",
    "marriage",
    "transactions"
  ],
  "era_tags": [
    "seventh-century-ah"
  ],
  "madhab_tags": [
    "shafii"
  ],
  "content_type_tags": [
    "ruling",
    "commentary"
  ],
  "keywords": [
    "rawdat al-talibin",
    "imam an-nawawi",
    "shafii fiqh reference",
    "comprehensive shafii",
    "nawawi shafii encyclopedia"
  ],
  "qa_passed": true,
  "qa_errors": []
}