{
  "number": 26,
  "title_en": "4. Remember your micronutrients",
  "title_ar": "",
  "content_en": "<p>Micronutrients (vitamins and minerals) are needed by the body in small amounts to perform important metabolic functions. The body cannot synthesize most of them, so a constant supply in the diet is very important. They are essential in glucose metabolism, to produce energy, and to synthesise many neurotransmitters, prostaglandins (hormone-like substances) and phospholipids. 55 Please refer to the Table of Micronutrients at the back of this book for more details concerning their dietary sources and the role each of them performs in the body. To get an adequate supply of vitamins and minerals: 52 Holford, 2005b. 53 Carper, 2001. 54 Imam Malik. 55 Holford, 2005b. •!• Eat your daily servings of fruits and vegetables. Vary the types, enjoy the different colours and include lots of dark green leafy vegetables. •!• Make nuts, seeds, beans and lentils part of your daily regime. Be aware that they are rich in calories, so if you are watching your weight, limit quantities to the lower amounts that may be recommended for your age and weight. •!• Replace refined grains with whole ones that are rich in B vitamins, the vital vitamins for mental performance, memory, mood, and energy production. We can now further understand why our Prophet (~ ) stressed the importance of eating whole grains rather than refined ones. •!• Avoid nutrient-robbers: these are the empty calorie foods like overly refined or processed food, fat-loaded fast foods, and foods with added synthetic flavouring and colouring.</p>",
  "subject_tags": [],
  "topic_tags": [],
  "era_tags": [],
  "madhab_tags": [],
  "content_type_tags": [
    "prose"
  ],
  "keywords": [],
  "source_lang": "en",
  "source_type": "pdf",
  "en_processed_from_source": true,
  "is_editorial": false,
  "qa_passed": false,
  "qa_errors": [
    "content_en too short: 242 words (min 300)"
  ],
  "title_id": "4. Ingat Mikronutrien Anda",
  "content_id": "<p>Mikronutrien (vitamin dan mineral) dibutuhkan oleh tubuh dalam jumlah kecil untuk menjalankan fungsi metabolisme yang penting. Tubuh tidak dapat menyintesis sebagian besarnya, sehingga pasokan yang konstan dalam diet sangat penting. Mikronutrien penting dalam metabolisme glukosa, untuk menghasilkan energi, dan untuk menyintesis banyak neurotransmiter, prostaglandin, dan fosfolipid. Untuk mendapatkan pasokan vitamin dan mineral yang cukup: •Makan porsi buah dan sayuran harian Anda. Variasikan jenisnya, nikmati berbagai warnanya, dan masukkan banyak sayuran berdaun hijau gelap. •Jadikan kacang-kacangan, biji-bijian, dan lentil sebagai bagian dari rutinitas harian Anda. •Gantikan biji-bijian olahan dengan biji-bijian utuh yang kaya vitamin B, vitamin vital untuk kinerja mental, memori, suasana hati, dan produksi energi. Kita sekarang dapat lebih memahami mengapa Nabi ﷺ menekankan pentingnya makan biji-bijian utuh daripada yang dihaluskan. •Hindari 'pencuri nutrisi': ini adalah makanan kalori kosong seperti makanan yang terlalu dihaluskan atau diproses, makanan cepat saji yang penuh lemak, dan makanan dengan perisa dan pewarna sintetis tambahan.</p>"
}