{
  "number": 3,
  "title_en": "The Philosophy of History: Natural Causes and Divine Providence",
  "title_ar": "فلسفة التاريخ: الأسباب الطبيعية والعناية الإلهية",
  "content_en": "<p>The philosophical framework of Al-Muqaddimah occupies an important position in the history of Islamic intellectual thought: it represents the most sustained attempt in the classical tradition to develop a systematic account of historical change that operates through natural causes while remaining within an Islamic theological worldview.</p>\n<p>Ibn Khaldun's approach to causation in history was neither purely supernatural nor purely naturalistic but reflected the Islamic philosophical synthesis developed by thinkers like al-Ghazali: God is the ultimate cause of all events, but He typically acts through created secondary causes — the natural and social forces that Ibn Khaldun analyzed. Understanding these secondary causes does not diminish divine sovereignty; rather, it reveals the regularities through which providence works.</p>\n<p>His concept of 'umran (human civilization or social organization) represents the subject matter of his new 'science' — a systematic study of the conditions and patterns of human social life. Like Aristotle's study of political organization, 'umran was for Ibn Khaldun a natural phenomenon governed by discernible patterns, not a mere aggregate of individual choices or divine interventions. The patterns he identified — the asabiyyah cycle, the economic dynamics of urban growth and decline, the relationship between climate and character — constitute the 'laws' of his science of civilization.</p>\n<p>Ibn Khaldun's position on the relationship between free will and historical necessity was nuanced. He did not believe that history was fully determined — individual choices matter, and religious commitment can alter the default trajectories. But he also recognized that certain patterns were extremely robust: the erosion of asabiyyah in settled conditions was virtually inevitable unless sustained by unusual discipline or religious renewal.</p>\n<p>This balance between pattern and agency, between natural necessity and human freedom, gives Ibn Khaldun's philosophy of history a sophistication that continues to attract philosophical attention. He avoided both the radical determinism that would make history a mere unfolding of fixed laws and the radical contingency that would make it an unintelligible sequence of arbitrary events.</p>",
  "qa_passed": true
}